pytyped/json/__init__.py
pytyped/json/common.py
pytyped/json/decoder.py
pytyped/json/encoder.py
pytyped/json/py.typed
pytyped_json-2.0.0.dist-info/LICENSE
pytyped_json-2.0.0.dist-info/METADATA
pytyped_json-2.0.0.dist-info/WHEEL
pytyped_json-2.0.0.dist-info/top_level.txt
pytyped_json-2.0.0.dist-info/RECORD
