Metadata-Version: 2.1
Name: pytyped-json
Version: 2.0.0
Summary: Type-Driven Development for Python: Automatic Extraction of JSON Decoders/Encoders for Python Types
Home-page: https://github.com/stasharrofi/pytyped/tree/master/pytyped-json
Author: Shahab Tasharrofi
Author-email: shahab.tasharrofi@gmail.com
Classifier: Programming Language :: Python :: 3
Classifier: License :: OSI Approved :: MIT License
Classifier: Operating System :: OS Independent
Requires-Python: >=3.6
License-File: LICENSE
Requires-Dist: python-dateutil>=2.8.1
Requires-Dist: pytyped-macros>=2.0.0
